{
    "config": {
        "csrf_token": "PIcEC7Spx651a4t1TufOWH2GLa8YQz6n",
        "viewer": {
            "biography": "",
            "external_url": null,
            "full_name": "\u00c1lfheim Yggdrasil",
            "has_phone_number": false,
            "has_profile_pic": true,
            "id": "13381472486",
            "is_joined_recently": false,
            "is_private": true,
            "profile_pic_url": "https://scontent-sjc3-1.cdninstagram.com/vp/0ce4091e4066d94b1643be4cb9d707c1/5E353EFC/t51.2885-19/s150x150/60238760_362073194513828_3769474637130366976_n.jpg?_nc_ht=scontent-sjc3-1.cdninstagram.com",
            "profile_pic_url_hd": "https://scontent-sjc3-1.cdninstagram.com/vp/f966dc2afdc64aac197e58d13414a8d6/5E32B20C/t51.2885-19/s320x320/60238760_362073194513828_3769474637130366976_n.jpg?_nc_ht=scontent-sjc3-1.cdninstagram.com",
            "username": "xnidhog",
            "badge_count": "{\"seq_id\": 116, \"badge_count\": 0, \"badge_count_at_ms\": 1570279212397}"
        },
        "viewerId": "13381472486"
    },
    "country_code": "US",
    "language_code": "zh-cn",
    "locale": "zh_CN",
    "entry_data": {
        "ProfilePage": [{
                    "logging_page_id": "profilePage_1508769542",
                    "show_suggested_profiles": false,
                    "show_follow_dialog": false,
                    "graphql": {
                        "user": {
                            "biography": "\u611b\u3068\u771f\u5b9f\u306e\u60aa\u3092\u8cab\u304f\n\u30e9\u30d6\u30ea\u30fc\u30c1\u30e3\u30fc\u30df\u30fc\u306a\u6575\u5f79\n\u53ea\u505a\u81ea\u5df1\u559c\u6b22\u7684\u4e8b\nsketches @nug.arukas  \n\u3010BusinessEmail\u3011:cosersakuragun@gmail.com",
                            "blocked_by_viewer": false,
                            "country_block": false,
                            "external_url": "https://m.facebook.com/sakuragun.official/",
                            "external_url_linkshimmed": "https://l.instagram.com/?u=https%3A%2F%2Fm.facebook.com%2Fsakuragun.official%2F\u0026e=ATMwUDGn7D1snh0xULS6Kp6jekKHGA5oy2q7k4p6P6L1mHLhHl0dXn5S7uIewq-6omDzrsRkebCieKig",
                            "edge_followed_by": {
                                "count": 536022
                            },
                            "followed_by_viewer": false,
                            "edge_follow": {
                                "count": 348
                            },
                            "follows_viewer": false,
                            "full_name": "\u6a31\u7fa4",
                            "has_channel": false,
                            "has_blocked_viewer": false,
                            "highlight_reel_count": 4,
                            "has_requested_viewer": false,
                            "id": "1508769542",
                            "is_business_account": false,
                            "is_joined_recently": false,
                            "business_category_name": null,
                            "is_private": false,
                            "is_verified": false,
                            "edge_mutual_followed_by": {
                                "count": 1,
                                "edges": [{
                                    "node": {
                                        "username": "real__yami"
                                    }
                                }]
                            },
                            "profile_pic_url": "https://scontent-sjc3-1.cdninstagram.com/vp/d907aea96bc1dcb1741ec0e744eb0ae6/5E2EA27C/t51.2885-19/s150x150/25007608_176454353093223_3123344451519381504_n.jpg?_nc_ht=scontent-sjc3-1.cdninstagram.com",
                            "profile_pic_url_hd": "https://scontent-sjc3-1.cdninstagram.com/vp/2e9873ab8cdf576579e20bc59b71cda0/5E38B18C/t51.2885-19/s320x320/25007608_176454353093223_3123344451519381504_n.jpg?_nc_ht=scontent-sjc3-1.cdninstagram.com",
                            "requested_by_viewer": false,
                            "username": "sakura.gun",
                            "connected_fb_page": null,
                            "edge_felix_video_timeline": {
                                "count": 0,
                                "page_info": {
                                    "has_next_page": false,
                                    "end_cursor": null
                                },
                                "edges": []
                            },
                            "edge_owner_to_timeline_media": {
                                "count": 1421,
                                "page_info": {
                                    "has_next_page": true,
                                    "end_cursor": "QVFEMFE0dWNNeTctcUJiNU9mS0djWUtvbXBiX3JuRHFtcVhpQWZJMWR5Q2VCMHRHRURUM2Z0cE5SVTk5aUFmeDZtZG9rdmMyMl9XSVFtajRFa1RfWTV3bg=="
                                },
                                "edges": [{
                                            "node": {
                                                "__typename": "GraphSidecar",
                                                "id": "2147379963354031995",
                                                "edge_media_to_caption": {
                                                    "edges": [{
                                                        "node": {
                                                            "text": "Happy friday!\ud83d\udc36"
                                                        }
                                                    }]
                                                },
                                                "shortcode": "B3NBrMJgid7",
                                                "edge_media_to_comment": {
                                                    "count": 192
                                                },
                                                "comments_disabled": false,
                                                "taken_at_timestamp": 1570207661,
                                                "dimensions": {
                                                    "height": 1350,
                                                    "width": 1080
                                                },
                                                "display_url": "https://scontent-sjc3-1.cdninstagram.com/vp/1b873c0d3fc424483f57b62c0b62381c/5E17D109/t51.2885-15/e35/p1080x1080/71679207_1433134266839826_3030796562254804268_n.jpg?_nc_ht=scontent-sjc3-1.cdninstagram.com\u0026_nc_cat=1",
                                                "edge_liked_by": {
                                                    "count": 23482
                                                },
                                                "edge_media_preview_like": {
                                                    "count": 23482
                                                },
                                                "location": null,
                                                "gating_info": null,
                                                "fact_check_information": null,
                                                "media_preview": null,
                                                "owner": {
                                                    "id": "1508769542",
                                                    "username": "sakura.gun"
                                                },
                                                "thumbnail_src": "https://scontent-sjc3-1.cdninstagram.com/vp/5ed22d35edc98e2297011b68a1cbb0ff/5E3BBCAD/t51.2885-15/sh0.08/e35/c0.180.1440.1440a/s640x640/71679207_1433134266839826_3030796562254804268_n.jpg?_nc_ht=scontent-sjc3-1.cdninstagram.com\u0026_nc_cat=1",
                                                "thumbnail_resources": [{
                                                    "src": "https://scontent-sjc3-1.cdninstagram.com/vp/272f4557f07472a2f3acf8abd9855f3a/5E29449D/t51.2885-15/e35/c0.180.1440.1440a/s150x150/71679207_1433134266839826_3030796562254804268_n.jpg?_nc_ht=scontent-sjc3-1.cdninstagram.com\u0026_nc_cat=1",
                                                    "config_width": 150,
                                                    "config_height": 150
                                                }, {
                                                    "src": "https://scontent-sjc3-1.cdninstagram.com/vp/97a1c0f9bbe5b12c8109ea2105d6e9c6/5E2FDF9B/t51.2885-15/e35/c0.180.1440.1440a/s240x240/71679207_1433134266839826_3030796562254804268_n.jpg?_nc_ht=scontent-sjc3-1.cdninstagram.com\u0026_nc_cat=1",
                                                    "config_width": 240,
                                                    "config_height": 240
                                                }, {
                                                    "src": "https://scontent-sjc3-1.cdninstagram.com/vp/335c460d9b8439a6bdfcc6552d876643/5E379FE5/t51.2885-15/e35/c0.180.1440.1440a/s320x320/71679207_1433134266839826_3030796562254804268_n.jpg?_nc_ht=scontent-sjc3-1.cdninstagram.com\u0026_nc_cat=1",
                                                    "config_width": 320,
                                                    "config_height": 320
                                                }, {
                                                    "src": "https://scontent-sjc3-1.cdninstagram.com/vp/edf008f8b2e151f9fffc74e90137ea97/5E3A9CA2/t51.2885-15/e35/c0.180.1440.1440a/s480x480/71679207_1433134266839826_3030796562254804268_n.jpg?_nc_ht=scontent-sjc3-1.cdninstagram.com\u0026_nc_cat=1",
                                                    "config_width": 480,
                                                    "config_height": 480
                                                }, {
                                                    "src": "https://scontent-sjc3-1.cdninstagram.com/vp/5ed22d35edc98e2297011b68a1cbb0ff/5E3BBCAD/t51.2885-15/sh0.08/e35/c0.180.1440.1440a/s640x640/71679207_1433134266839826_3030796562254804268_n.jpg?_nc_ht=scontent-sjc3-1.cdninstagram.com\u0026_nc_cat=1",
                                                    "config_width": 640,
                                                    "config_height": 640
                                                }],
                                                "is_video": false,
                                                "accessibility_caption": "\u56fe\u7247\u4e2d\u53ef\u80fd\u6709\uff1a\u4e00\u4eba\u6216\u591a\u4eba\u548c\u7279\u5199"
                                            }
                                        }, {
                                            "node": {
                                                "__typename": "GraphImage",
                                                "id": "2145576807930267927",
                                                "edge_media_to_caption": {
                                                    "edges": [{
                                                        "node": {
                                                            "text": "\ud83c\udf3b"
                                                        }
                                                    }]
                                                },
                                                "shortcode": "B3Gnr0zAAkX",
                                                "edge_media_to_comment": {
                                                    "count": 180
                                                },
                                                "comments_disabled": false,
                                                "taken_at_timestamp": 1569992708,
                                                "dimensions": {
                                                    "height": 1350,
                                                    "width": 1080
                                                },
                                                "display_url": "https://scontent-sjc3-1.cdninstagram.com/vp/a0e71eee79dcc270b91ea48bcf0f6519/5E2A6313/t51.2885-15/e35/p1080x1080/69880200_3131142753594832_8791794781920042188_n.jpg?_nc_ht=scontent-sjc3-1.cdninstagram.com\u0026_nc_cat=104",
                                                "edge_liked_by": {
                                                    "count": 23278
                                                },
                                                "edge_media_preview_like": {
                                                    "count": 23278
                                                },
                                                "location": null,
                                                "gating_info": null,
                                                "fact_check_information": null,
                                                "media_preview": "ACEq1YPvA4x1rBv5DLcP6Lx+A4/nmtNY8jG8gDvxmsi2w83OSpJz+ef170XfUY5If3e71BP+H4n0rpLRtyKSedi/y5qm7DG0L94gDA9eM/QetTP+6Q7DznaOg6Urjehd8xfUfnRWDsf+8Pzoqbsk1LuNnXy4yFU/e7Ej0HHfvVW2s1tsn7xP8quO1MzxWqQytcSeSm+MdTyQM4FJG4uAykg4GQwHb3/HtTDMUDHqvp3HPp6Hp9cVZj2yIdgCH2/+t6iuZrW3mX0M7Y3rRVr7NRW1mZ3LLnjrTsYHNVpuo+tWZOn41oMpJbEMScNnpn0/z+VWreEQjHWg/eX6n+VO7D61ny3dx3srIdge9FNorQk//9k=",
                                                "owner": {
                                                    "id": "1508769542",
                                                    "username": "sakura.gun"
                                                },
                                                "thumbnail_src": "https://scontent-sjc3-1.cdninstagram.com/vp/7331321c81d261ca21632e344b0b5555/5E3067B7/t51.2885-15/sh0.08/e35/c0.180.1440.1440a/s640x640/69880200_3131142753594832_8791794781920042188_n.jpg?_nc_ht=scontent-sjc3-1.cdninstagram.com\u0026_nc_cat=104",
                                                "thumbnail_resources": [{
                                                    "src": "https://scontent-sjc3-1.cdninstagram.com/vp/cca307bdcb2cd6dc478d2e9b5b33c966/5E3BC187/t51.2885-15/e35/c0.180.1440.1440a/s150x150/69880200_3131142753594832_8791794781920042188_n.jpg?_nc_ht=scontent-sjc3-1.cdninstagram.com\u0026_nc_cat=104",
                                                    "config_width": 150,
                                                    "config_height": 150
                                                }, {
                                                    "src": "https://scontent-sjc3-1.cdninstagram.com/vp/1e35c71498c64151dddb608e584d7865/5E283D81/t51.2885-15/e35/c0.180.1440.1440a/s240x240/69880200_3131142753594832_8791794781920042188_n.jpg?_nc_ht=scontent-sjc3-1.cdninstagram.com\u0026_nc_cat=104",
                                                    "config_width": 240,
                                                    "config_height": 240
                                                }, {
                                                    "src": "https://scontent-sjc3-1.cdninstagram.com/vp/074d03bfe20cad437c25419c15bb6ca6/5E2856FF/t51.2885-15/e35/c0.180.1440.1440a/s320x320/69880200_3131142753594832_8791794781920042188_n.jpg?_nc_ht=scontent-sjc3-1.cdninstagram.com\u0026_nc_cat=104",
                                                    "config_width": 320,
                                                    "config_height": 320
                                                }, {
                                                    "src": "https://scontent-sjc3-1.cdninstagram.com/vp/69938b61b9c5598aad3f8da7216c0c79/5E287DB8/t51.2885-15/e35/c0.180.1440.1440a/s480x480/69880200_3131142753594832_8791794781920042188_n.jpg?_nc_ht=scontent-sjc3-1.cdninstagram.com\u0026_nc_cat=104",
                                                    "config_width": 480,
                                                    "config_height": 480
                                                }, {
                                                    "src": "https://scontent-sjc3-1.cdninstagram.com/vp/7331321c81d261ca21632e344b0b5555/5E3067B7/t51.2885-15/sh0.08/e35/c0.180.1440.1440a/s640x640/69880200_3131142753594832_8791794781920042188_n.jpg?_nc_ht=scontent-sjc3-1.cdninstagram.com\u0026_nc_cat=104",
                                                    "config_width": 640,
                                                    "config_height": 640
                                                }],
                                                "is_video": false,
                                                "accessibility_caption": "\u56fe\u7247\u4e2d\u53ef\u80fd\u6709\uff1a\u4e00\u4eba\u6216\u591a\u4eba\u3001\u82b1\u3001\u690d\u7269\u3001\u6237\u5916\u548c\u5927\u81ea\u7136"
                                            }
                                        }, {
                                            "node": {
                                                "__typename": "GraphSidecar",
                                                "id": "2144803696612041947",
                                                "edge_media_to_caption": {
                                                    "edges": [{
                                                        "node": {
                                                            "text": "With my cute \u9992\u5934\ud83d\udc4c\ud83c\udffb\nAlso Happy birthday to China!\ud83c\udde8\ud83c\uddf3I love CHINA\u2764\ufe0f"
                                                        }
                                                    }]
                                                },
                                                "shortcode": "B3D35kxgWTb",
                                                "edge_media_to_comment": {
                                                    "count": 263
                                                },
                                                "comments_disabled": false,
                                                "taken_at_timestamp": 1569900546,
                                                "dimensions": {
                                                    "height": 1080,
                                                    "width": 1080
                                                },
                                                "display_url": "https://scontent-sjc3-1.cdninstagram.com/vp/abfad818d7aaa2a862f7d5d268434f29/5E26F0C8/t51.2885-15/e35/s1080x1080/71180304_201539727504968_7155551362974106418_n.jpg?_nc_ht=scontent-sjc3-1.cdninstagram.com\u0026_nc_cat=108",
                                                "edge_liked_by": {
                                                    "count": 33386
                                                },
                                                "edge_media_preview_like": {
                                                    "count": 33386
                                                },
                                                "location": null,
                                                "gating_info": null,
                                                "fact_check_information": null,
                                                "media_preview": null,
                                                "owner": {
                                                    "id": "1508769542",
                                                    "username": "sakura.gun"
                                                },
                                                "thumbnail_src": "https://scontent-sjc3-1.cdninstagram.com/vp/fc4e93d73c68dc5526153ffe38027d7b/5E2ACE7F/t51.2885-15/sh0.08/e35/s640x640/71180304_201539727504968_7155551362974106418_n.jpg?_nc_ht=scontent-sjc3-1.cdninstagram.com\u0026_nc_cat=108",
                                                "thumbnail_resources": [{
                                                            "src": "https://scontent-sjc3-1.cdninstagram.com/vp/fda388bc67932399fc0cadf743816319/5E18FED8/t51.2885-15/e35/s150x150/71180304_201539727504968_7155551362974106418_n.jpg?_nc_ht=scontent-sjc3-1.cdninstagram.com\u0026_nc_cat=108",
                                                            "config_width": 150,
                                                            "config_height": 150
                                                        }, {
                                                            "src": "ht…